dictionary/__init__.py
dictionary/dictionary.py
bartu_teber_cs_453_hw1-3.3.0.dist-info/METADATA
bartu_teber_cs_453_hw1-3.3.0.dist-info/WHEEL
bartu_teber_cs_453_hw1-3.3.0.dist-info/top_level.txt
bartu_teber_cs_453_hw1-3.3.0.dist-info/RECORD
