Metadata-Version: 2.1
Name: bartu-teber-cs-453-hw1
Version: 3.3.0
Summary: UNKNOWN
Author: Bartu Teber
License: UNKNOWN
Platform: UNKNOWN
Requires-Python: >=3.8
Requires-Dist: requests (>=2.23.0)
